{
  "api": "d3.shuffle",
  "blocks": {
    "1243323": {
      "userId": "mbostock",
      "description": "Merge Sort",
      "thumbnail": "https://gist.githubusercontent.com/mbostock/1243323/raw/cf5a3130984da4b5db2603c8c7da380794f8a25f/thumbnail.png"
    },
    "8981451": {
      "userId": "milroc",
      "description": " ",
      "thumbnail": "https://gist.githubusercontent.com/milroc/8981451/raw/da0aa8e767b28f6e50f0c6152d33cc3fa5278317/thumbnail.png"
    }
  },
  "count": 2,
  "coocurance": {
    "d3.select": 2,
    "d3.range": 2,
    "d3.scale": 2,
    "d3.scale.linear": 2,
    "d3.values": 1,
    "d3.hexbin": 1,
    "d3.event": 1,
    "d3.max": 1,
    "d3.set": 1,
    "d3.format": 1,
    "d3.rgb": 1,
    "d3.functor": 1,
    "d3.rebind": 1,
    "d3.scale.sqrt": 1,
    "d3.scale.ordinal": 1,
    "d3.scale.category": 1,
    "d3.svg": 1,
    "d3.svg.axis": 1,
    "d3.svg.brush": 1,
    "d3.layout": 1,
    "d3.layout.force": 1,
    "d3.geo": 1,
    "d3.geom": 1,
    "d3.geom.quadtree": 1,
    "d3.mouse": 1,
    "d3.timer": 1,
    "d3.timer.flush": 1,
    "d3.interpolate": 1,
    "d3.interpolateNumber": 1,
    "d3.interpolateHcl": 1,
    "d3.ascending": 1,
    "d3.min": 1,
    "d3.extent": 1,
    "d3.sum": 1,
    "d3.quantile": 1,
    "d3.nest": 1,
    "d3.scale.quantize": 1,
    "d3.svg.line": 1,
    "d3.svg.area": 1,
    "d3.svg.arc": 1,
    "d3.time": 1,
    "d3.time.format": 1,
    "d3.layout.pie": 1,
    "d3.layout.stack": 1,
    "d3.geo.path": 1,
    "d3.behavior": 1,
    "d3.behavior.zoom": 1,
    "d3.box": 1,
    "d3.selectAll": 1,
    "d3.shuffle": 1,
    "d3.time.hour": 1,
    "d3.dispatch": 1
  }
}